ezsend/__init__.py
ezsend-0.0.4.dist-info/LICENSE.txt
ezsend-0.0.4.dist-info/METADATA
ezsend-0.0.4.dist-info/WHEEL
ezsend-0.0.4.dist-info/top_level.txt
ezsend-0.0.4.dist-info/RECORD
