Metadata-Version: 2.1
Name: ezsend
Version: 0.0.4
Summary: Ezsend, the easiest way to send mail and texts in python
Home-page: https://github.com/BouncyBird/ezsend
Author: Eshan Nalajala
Author-email: eshan.nalajala@gmail.com
License: UNKNOWN
Platform: UNKNOWN
Classifier: Programming Language :: Python :: 3
Classifier: License :: OSI Approved :: MIT License
Classifier: Operating System :: OS Independent
Requires-Python: >=3.6
Requires-Dist: sys
Requires-Dist: re
Requires-Dist: smtplib
Requires-Dist: time
